testzeus_hercules/VERSION
testzeus_hercules/__init__.py
testzeus_hercules/__main__.py
testzeus_hercules/config.py
testzeus_hercules/core/__init__.py
testzeus_hercules/core/agents/__init__.py
testzeus_hercules/core/agents/browser_nav_agent.py
testzeus_hercules/core/agents/high_level_planner_agent.py
testzeus_hercules/core/agents_llm_config.py
testzeus_hercules/core/autogen_simple_wrapper.py
testzeus_hercules/core/memory/__init__.py
testzeus_hercules/core/memory/prompt_compressor.py
testzeus_hercules/core/memory/static_ltm.py
testzeus_hercules/core/notification_manager.py
testzeus_hercules/core/playwright_manager.py
testzeus_hercules/core/post_process_responses.py
testzeus_hercules/core/prompts.py
testzeus_hercules/core/runner.py
testzeus_hercules/core/skills/__init__.py
testzeus_hercules/core/skills/api_calls.py
testzeus_hercules/core/skills/captcha_solver.py
testzeus_hercules/core/skills/click_using_selector.py
testzeus_hercules/core/skills/dropdown_using_selector.py
testzeus_hercules/core/skills/enter_date_time.py
testzeus_hercules/core/skills/enter_text_and_click.py
testzeus_hercules/core/skills/enter_text_using_selector.py
testzeus_hercules/core/skills/get_dom_with_content_type.py
testzeus_hercules/core/skills/get_url.py
testzeus_hercules/core/skills/get_user_input.py
testzeus_hercules/core/skills/hover.py
testzeus_hercules/core/skills/open_url.py
testzeus_hercules/core/skills/pdf_text_extractor.py
testzeus_hercules/core/skills/press_key_combination.py
testzeus_hercules/core/skills/set_slider_value.py
testzeus_hercules/core/skills/skill_registry.py
testzeus_hercules/core/skills/sql_calls.py
testzeus_hercules/core/skills/upload_file.py
testzeus_hercules/core/ui_manager.py
testzeus_hercules/interactive.py
testzeus_hercules/js/injectOverlay.js
testzeus_hercules/telemetry.py
testzeus_hercules/utils/__init__.py
testzeus_hercules/utils/autogen_sequential_function_call.py
testzeus_hercules/utils/cli_helper.py
testzeus_hercules/utils/detect_llm_loops.py
testzeus_hercules-0.1.9.dist-info/LICENSE
testzeus_hercules-0.1.9.dist-info/METADATA
testzeus_hercules-0.1.9.dist-info/WHEEL
testzeus_hercules-0.1.9.dist-info/entry_points.txt
testzeus_hercules-0.1.9.dist-info/RECORD
