Metadata-Version: 2.1
Name: testzeus-hercules
Version: 0.1.9
Summary: Hercules: The World's First Open-Source AI Agent for End-to-End Testing
Home-page: https://testzeus.com/hercules
Keywords: AI,end-to-end testing,automation,Hercules,TestZeus
Author: Shriyansh Agnihotri
Author-email: shriyansh@testzeus.com
Requires-Python: >=3.11,<3.13
Classifier: Programming Language :: Python :: 3
Classifier: Programming Language :: Python :: 3.11
Classifier: Programming Language :: Python :: 3.12
Requires-Dist: aiomysql (>=0.2.0,<0.3.0)
Requires-Dist: aiosqlite (>=0.20.0,<0.21.0)
Requires-Dist: annotated-types (>=0.6.0,<0.7.0)
Requires-Dist: anthropic (>=0.23.1,<0.24.0)
Requires-Dist: anyio (>=4.3.0,<5.0.0)
Requires-Dist: asyncpg (>=0.30.0,<0.31.0)
Requires-Dist: autogen-agentchat[anthropic,graph,groq,long-context] (>=0.2.0,<0.3.0)
Requires-Dist: build (>=1.2.2.post1,<2.0.0)
Requires-Dist: cachetools (>=5.3.3,<6.0.0)
Requires-Dist: certifi (>=2024.2.2,<2025.0.0)
Requires-Dist: cffi (>=1.16.0,<2.0.0)
Requires-Dist: charset-normalizer (>=3.3.2,<4.0.0)
Requires-Dist: click (>=8.1.7,<9.0.0)
Requires-Dist: cryptography (>=42.0.8,<43.0.0)
Requires-Dist: diskcache (>=5.6.3,<6.0.0)
Requires-Dist: distro (>=1.9.0,<2.0.0)
Requires-Dist: dnspython (>=2.6.1,<3.0.0)
Requires-Dist: docker (>=7.0.0,<8.0.0)
Requires-Dist: email-validator (>=2.2.0,<3.0.0)
Requires-Dist: filelock (>=3.13.3,<4.0.0)
Requires-Dist: fsspec (>=2024.3.1,<2025.0.0)
Requires-Dist: google-ai-generativelanguage (>=0.6.2,<0.7.0)
Requires-Dist: google-api-core (>=2.19.0,<3.0.0)
Requires-Dist: google-api-python-client (>=2.127.0,<3.0.0)
Requires-Dist: google-auth (>=2.29.0,<3.0.0)
Requires-Dist: google-auth-httplib2 (>=0.2.0,<0.3.0)
Requires-Dist: google-generativeai (>=0.5.1,<0.6.0)
Requires-Dist: googleapis-common-protos (>=1.63.0,<2.0.0)
Requires-Dist: greenlet (>=3.0.3,<4.0.0)
Requires-Dist: grpcio (>=1.63.0,<2.0.0)
Requires-Dist: grpcio-status (>=1.62.2,<2.0.0)
Requires-Dist: h11 (>=0.14.0,<0.15.0)
Requires-Dist: httpcore (>=1.0.4,<2.0.0)
Requires-Dist: httplib2 (>=0.22.0,<0.23.0)
Requires-Dist: httptools (>=0.6.1,<0.7.0)
Requires-Dist: httpx (>=0.27.0,<0.28.0)
Requires-Dist: huggingface-hub (>=0.22.2,<0.23.0)
Requires-Dist: idna (>=3.6,<4.0)
Requires-Dist: jinja2 (>=3.1.4,<4.0.0)
Requires-Dist: joblib (>=1.3.2,<2.0.0)
Requires-Dist: junit2html (>=31.0.2,<32.0.0)
Requires-Dist: junitparser (>=3.2.0,<4.0.0)
Requires-Dist: markdown-it-py (>=3.0.0,<4.0.0)
Requires-Dist: markupsafe (>=2.1.5,<3.0.0)
Requires-Dist: mdurl (>=0.1.2,<0.2.0)
Requires-Dist: nest-asyncio (>=1.6.0,<2.0.0)
Requires-Dist: nltk (>=3.8.1,<4.0.0)
Requires-Dist: numpy (>=1.26.4,<2.0.0)
Requires-Dist: openai (>=1.47.0,<2.0.0)
Requires-Dist: packaging (>=23.2,<24.0)
Requires-Dist: pdfminer-six (>=20231228,<20231229)
Requires-Dist: pdfplumber (>=0.11.1,<0.12.0)
Requires-Dist: pillow (>=10.3.0,<11.0.0)
Requires-Dist: playwright (>=1.44.0,<2.0.0)
Requires-Dist: playwright-recaptcha (>=0.5.1,<0.6.0)
Requires-Dist: proto-plus (>=1.23.0,<2.0.0)
Requires-Dist: protobuf (>=4.25.3,<5.0.0)
Requires-Dist: pyasn1 (>=0.6.0,<0.7.0)
Requires-Dist: pyasn1-modules (>=0.4.0,<0.5.0)
Requires-Dist: pycparser (>=2.22,<3.0)
Requires-Dist: pydantic (>=2.6.2,<3.0.0)
Requires-Dist: pydantic-core (>=2.16.3,<3.0.0)
Requires-Dist: pyee (>=11.1.0,<12.0.0)
Requires-Dist: pygments (>=2.18.0,<3.0.0)
Requires-Dist: pymupdf (>=1.24.13,<2.0.0)
Requires-Dist: pyparsing (>=3.1.2,<4.0.0)
Requires-Dist: pypdfium2 (>=4.30.0,<5.0.0)
Requires-Dist: pytest-playwright (>=0.5.2,<0.6.0)
Requires-Dist: python-dotenv (>=1.0.0,<2.0.0)
Requires-Dist: python-json-logger (>=2.0.7,<3.0.0)
Requires-Dist: python-multipart (>=0.0.9,<0.0.10)
Requires-Dist: pyyaml (>=6.0.1,<7.0.0)
Requires-Dist: regex (>=2023.12.25,<2024.0.0)
Requires-Dist: requests (>=2.31.0,<3.0.0)
Requires-Dist: rich (>=13.7.1,<14.0.0)
Requires-Dist: rsa (>=4.9,<5.0)
Requires-Dist: sentry-sdk (>=2.18.0,<3.0.0)
Requires-Dist: setuptools (>=75.3.0,<76.0.0)
Requires-Dist: shellingham (>=1.5.4,<2.0.0)
Requires-Dist: sniffio (>=1.3.1,<2.0.0)
Requires-Dist: sqlalchemy (>=2.0.36,<3.0.0)
Requires-Dist: starlette (>=0.37.2,<0.38.0)
Requires-Dist: tabulate (>=0.9.0,<0.10.0)
Requires-Dist: termcolor (>=2.4.0,<3.0.0)
Requires-Dist: tiktoken (>=0.6.0,<0.7.0)
Requires-Dist: tokenizers (>=0.15.2,<0.16.0)
Requires-Dist: tqdm (>=4.66.2,<5.0.0)
Requires-Dist: twine (>=5.1.1,<6.0.0)
Requires-Dist: typer (>=0.12.3,<0.13.0)
Requires-Dist: typing-extensions (>=4.12.2,<5.0.0)
Requires-Dist: uritemplate (>=4.1.1,<5.0.0)
Requires-Dist: urllib3 (>=2.2.3,<3.0.0)
Requires-Dist: uvicorn (>=0.30.3,<0.31.0)
Requires-Dist: uvloop (>=0.21.0,<0.22.0)
Requires-Dist: watchfiles (>=0.24.0,<0.25.0)
Requires-Dist: websockets (>=13.1,<14.0)
Requires-Dist: wheel (>=0.44.0,<0.45.0)
Project-URL: Documentation, https://testzeus.com/hercules/docs
Project-URL: Repository, https://github.com/testzeus/testzeus-hercules
